pySimpleWorkflow/__init__.py
pySimpleWorkflow/flowchart.py
pySimpleWorkflow/step.py
pySimpleWorkflow/workflow.py
tests/__init__.py
tests/test_workflow.py
pySimpleWorkflow-0.6.dist-info/LICENSE
pySimpleWorkflow-0.6.dist-info/METADATA
pySimpleWorkflow-0.6.dist-info/WHEEL
pySimpleWorkflow-0.6.dist-info/top_level.txt
pySimpleWorkflow-0.6.dist-info/RECORD
