Metadata-Version: 2.1
Name: pySimpleWorkflow
Version: 0.6
Summary: manage a workflow written in csv
Home-page: https://github.com/20centcroak/pyWorkflow
Author: 20centCroak
Author-email: 
License: UNKNOWN
Platform: UNKNOWN
Classifier: Programming Language :: Python :: 3
Classifier: License :: OSI Approved :: MIT License
Classifier: Operating System :: OS Independent
Requires-Python: >=3.6
Requires-Dist: pyBaseApp
Requires-Dist: pandas
Requires-Dist: networkx
